{
  "id": "n8n-dropbox",
  "name": "Dropbox",
  "description": "Access data on Dropbox",
  "category": "storage",
  "iconName": "LuPackage",
  "version": 11,
  "lastVerified": "2026-06-11",
  "status": "draft",
  "auth": {
    "type": "oauth2",
    "provider": "dropbox",
    "credentialType": "dropbox",
    "fallback": {
      "type": "header",
      "credentialType": "http_header_auth"
    }
  },
  "baseUrl": "https://api.dropboxapi.com/2",
  "endpoints": [
    {
      "id": "file_copy",
      "label": "Copy File",
      "method": "POST",
      "path": "/file",
      "fields": [
        {
          "id": "path",
          "label": "From Path",
          "type": "text",
          "required": true,
          "placeholder": "/invoices/original.txt",
          "description": "The path of file or folder to copy"
        },
        {
          "id": "toPath",
          "label": "To Path",
          "type": "text",
          "required": true,
          "placeholder": "/invoices/copy.txt",
          "description": "The destination path of file or folder"
        }
      ],
      "group": "File",
      "description": "[unverified path] Copy a file"
    },
    {
      "id": "file_delete",
      "label": "Delete File",
      "method": "DELETE",
      "path": "/file",
      "fields": [
        {
          "id": "path",
          "label": "Delete Path",
          "type": "text",
          "required": true,
          "placeholder": "/invoices/2019/invoice_1.pdf",
          "description": "The path to delete. Can be a single file or a whole folder."
        }
      ],
      "group": "File",
      "description": "[unverified path] Delete a file"
    },
    {
      "id": "file_download",
      "label": "Download File",
      "method": "POST",
      "path": "/https:/content.dropboxapi.com/2/files/download",
      "fields": [
        {
          "id": "path",
          "label": "File Path",
          "type": "text",
          "required": true,
          "placeholder": "/invoices/2019/invoice_1.pdf",
          "description": "The file path of the file to download. Has to contain the full path."
        },
        {
          "id": "binaryPropertyName",
          "label": "Put Output File in Field",
          "type": "text",
          "required": true,
          "defaultValue": "data"
        }
      ],
      "group": "File",
      "description": "Download a file"
    },
    {
      "id": "file_move",
      "label": "Move File",
      "method": "PATCH",
      "path": "/file",
      "fields": [
        {
          "id": "path",
          "label": "From Path",
          "type": "text",
          "required": true,
          "placeholder": "/invoices/old_name.txt",
          "description": "The path of file or folder to move"
        },
        {
          "id": "toPath",
          "label": "To Path",
          "type": "text",
          "required": true,
          "placeholder": "/invoices/new_name.txt",
          "description": "The new path of file or folder"
        }
      ],
      "group": "File",
      "description": "[unverified path] Move a file"
    },
    {
      "id": "file_upload",
      "label": "Upload File",
      "method": "POST",
      "path": "/https:/content.dropboxapi.com/2/files/upload",
      "fields": [
        {
          "id": "path",
          "label": "File Path",
          "type": "text",
          "required": true,
          "placeholder": "/invoices/2019/invoice_1.pdf",
          "description": "The file path of the file to upload. Has to contain the full path. The parent folder has to exist. Existing files get overwritten."
        },
        {
          "id": "binaryData",
          "label": "Binary File",
          "type": "toggle",
          "description": "Whether the data to upload should be taken from binary field",
          "defaultValue": false
        },
        {
          "id": "fileContent",
          "label": "File Content",
          "type": "text",
          "description": "The text content of the file to upload"
        },
        {
          "id": "binaryPropertyName",
          "label": "Input Binary Field",
          "type": "text",
          "required": true,
          "defaultValue": "data"
        }
      ],
      "group": "File",
      "description": "Upload a file"
    },
    {
      "id": "folder_copy",
      "label": "Copy Folder",
      "method": "POST",
      "path": "/folder",
      "fields": [
        {
          "id": "path",
          "label": "From Path",
          "type": "text",
          "required": true,
          "placeholder": "/invoices/original.txt",
          "description": "The path of file or folder to copy"
        },
        {
          "id": "toPath",
          "label": "To Path",
          "type": "text",
          "required": true,
          "placeholder": "/invoices/copy.txt",
          "description": "The destination path of file or folder"
        }
      ],
      "group": "Folder",
      "description": "[unverified path] Copy a folder"
    },
    {
      "id": "folder_create",
      "label": "Create Folder",
      "method": "POST",
      "path": "/https:/api.dropboxapi.com/2/files/create_folder_v2",
      "fields": [
        {
          "id": "path",
          "label": "Folder",
          "type": "text",
          "required": true,
          "placeholder": "/invoices/2019",
          "description": "The folder to create. The parent folder has to exist."
        }
      ],
      "group": "Folder",
      "description": "Create a folder"
    },
    {
      "id": "folder_delete",
      "label": "Delete Folder",
      "method": "DELETE",
      "path": "/folder",
      "fields": [
        {
          "id": "path",
          "label": "Delete Path",
          "type": "text",
          "required": true,
          "placeholder": "/invoices/2019/invoice_1.pdf",
          "description": "The path to delete. Can be a single file or a whole folder."
        }
      ],
      "group": "Folder",
      "description": "[unverified path] Delete a folder"
    },
    {
      "id": "folder_list",
      "label": "List Folder",
      "method": "POST",
      "path": "/https:/api.dropboxapi.com/2/files/list_folder",
      "fields": [
        {
          "id": "path",
          "label": "Folder Path",
          "type": "text",
          "placeholder": "/invoices/2019/",
          "description": "The path of which to list the content"
        },
        {
          "id": "returnAll",
          "label": "Return All",
          "type": "toggle",
          "description": "Whether to return all results or only up to a given limit",
          "defaultValue": false
        },
        {
          "id": "limit",
          "label": "Limit",
          "type": "number",
          "description": "Max number of results to return",
          "defaultValue": 100
        },
        {
          "id": "filters",
          "label": "Filters",
          "type": "json",
          "placeholder": "Add Filter",
          "description": "(JSON object; supported keys: include_deleted, include_has_explicit_shared_members, include_mounted_folders, include_non_downloadable_files, recursive)"
        }
      ],
      "group": "Folder",
      "description": "Return the files and folders in a given folder"
    },
    {
      "id": "folder_move",
      "label": "Move Folder",
      "method": "PATCH",
      "path": "/folder",
      "fields": [
        {
          "id": "path",
          "label": "From Path",
          "type": "text",
          "required": true,
          "placeholder": "/invoices/old_name.txt",
          "description": "The path of file or folder to move"
        },
        {
          "id": "toPath",
          "label": "To Path",
          "type": "text",
          "required": true,
          "placeholder": "/invoices/new_name.txt",
          "description": "The new path of file or folder"
        }
      ],
      "group": "Folder",
      "description": "[unverified path] Move a folder"
    },
    {
      "id": "search_query",
      "label": "Query Search",
      "method": "POST",
      "path": "/https:/api.dropboxapi.com/2/files/search_v2",
      "fields": [
        {
          "id": "query",
          "label": "Query",
          "type": "text",
          "required": true,
          "description": "The string to search for. May match across multiple fields based on the request arguments."
        },
        {
          "id": "fileStatus",
          "label": "File Status",
          "type": "select",
          "description": "The string to search for. May match across multiple fields based on the request arguments.",
          "defaultValue": "active",
          "options": [
            {
              "value": "active",
              "label": "Active"
            },
            {
              "value": "deleted",
              "label": "Deleted"
            }
          ]
        },
        {
          "id": "returnAll",
          "label": "Return All",
          "type": "toggle",
          "description": "Whether to return all results or only up to a given limit",
          "defaultValue": false
        },
        {
          "id": "limit",
          "label": "Limit",
          "type": "number",
          "description": "Max number of results to return",
          "defaultValue": 100
        },
        {
          "id": "simple",
          "label": "Simplify",
          "type": "toggle",
          "description": "Whether to return a simplified version of the response instead of the raw data",
          "defaultValue": true
        },
        {
          "id": "filters",
          "label": "Filters",
          "type": "json",
          "placeholder": "Add Filter",
          "description": "(JSON object; supported keys: file_categories, file_extensions, path)"
        }
      ],
      "group": "Search",
      "description": "Query"
    }
  ]
}
