{
  "id": "n8n-totp",
  "name": "TOTP",
  "description": "Generate a time-based one-time password",
  "category": "productivity",
  "iconName": "LuPackage",
  "version": 1,
  "lastVerified": "2026-05-17",
  "status": "draft",
  "auth": {
    "type": "header",
    "credentialType": "http_header_auth"
  },
  "baseUrl": "",
  "endpoints": [
    {
      "id": "default_generate_secret",
      "label": "Generate Secret",
      "method": "GET",
      "path": "/",
      "fields": [
        {
          "id": "options",
          "label": "Options",
          "type": "json",
          "in": "query",
          "placeholder": "Add option"
        }
      ]
    }
  ]
}
